CHANGELOG
LICENSE
MANIFEST.in
README.rst
product.xml
sale.xml
setup.cfg
setup.py
website.xml
./__init__.py
./cart.py
./channel.py
./forms.py
./product.py
./product.xml
./sale.py
./sale.xml
./signals.py
./tryton.cfg
./website.py
./website.xml
./locale/de_DE.po
./tests/__init__.py
./tests/scenario.rst
./tests/test_cart.py
./tests/test_product.py
./tests/test_website.py
./view/product_form_nereid.xml
./view/website_view_form.xml
locale/de_DE.po
trytond_nereid_cart_b2c.egg-info/PKG-INFO
trytond_nereid_cart_b2c.egg-info/SOURCES.txt
trytond_nereid_cart_b2c.egg-info/dependency_links.txt
trytond_nereid_cart_b2c.egg-info/entry_points.txt
trytond_nereid_cart_b2c.egg-info/not-zip-safe
trytond_nereid_cart_b2c.egg-info/requires.txt
trytond_nereid_cart_b2c.egg-info/top_level.txt
view/product_form_nereid.xml
view/website_view_form.xml